perf_tool/__init__.py
perf_tool-0.9.1.dist-info/LICENSE
perf_tool-0.9.1.dist-info/METADATA
perf_tool-0.9.1.dist-info/WHEEL
perf_tool-0.9.1.dist-info/top_level.txt
perf_tool-0.9.1.dist-info/RECORD
