Metadata-Version: 2.1
Name: perf-tool
Version: 0.9.1
Summary: Performance investigation tool
Home-page: https://https://github.com/glaucouri/perf_tool
Author: Glauco Uri
Author-email: glauco@uriland.it
License: UNKNOWN
Platform: UNKNOWN
Classifier: Programming Language :: Python :: 2.7
Classifier: Programming Language :: Python :: 3
Classifier: Programming Language :: Python :: 3.6
Classifier: Programming Language :: Python :: 3.7
Classifier: Programming Language :: Python :: 3.8
Classifier: Programming Language :: Python :: 3.9
Classifier: License :: OSI Approved :: MIT License
Classifier: Operating System :: OS Independent
Requires-Python: >=2.7
